testingo/__init__.py
testingo/py.typed
testingo-0.0.6.dist-info/METADATA
testingo-0.0.6.dist-info/WHEEL
testingo-0.0.6.dist-info/licenses/LICENSE
testingo-0.0.6.dist-info/RECORD
