Metadata-Version: 2.1
Name: testingo
Version: 0.0.6
Project-URL: Documentation, https://ahuang11.github.io/testingo/
Project-URL: Source, https://github.com/ahuang11/testingo
Author-email: testingo <king.arthur@camelot.bt>
License-File: LICENSE
Classifier: Programming Language :: Python :: 3 :: Only
Requires-Python: >=3.11
